setup.py
pyco_orm.egg-info/PKG-INFO
pyco_orm.egg-info/SOURCES.txt
pyco_orm.egg-info/dependency_links.txt
pyco_orm.egg-info/not-zip-safe
pyco_orm.egg-info/requires.txt
pyco_orm.egg-info/top_level.txt
pyco_sqlalchemy/__init__.py
pyco_sqlalchemy/_base.py
pyco_sqlalchemy/_errors.py
pyco_sqlalchemy/_flask.py
pyco_sqlalchemy/_protos.py
pyco_sqlalchemy/_pymysql.py
pyco_sqlalchemy/_types.py
pyco_sqlalchemy/regex.py
pyco_sqlalchemy/utils.py