Metadata-Version: 2.1
Name: pyco-orm
Version: 2.1.3
Summary: Simple ORM BaseModel for Flask depends on SqlAlchemy
Home-page: https://github.com/dodoru/pyco-sqlalchemy
Author: Nico Ning
Author-email: dodoru@foxmail.com
License: MIT
Platform: any
Classifier: License :: OSI Approved :: MIT License
Classifier: Operating System :: OS Independent
Classifier: Programming Language :: Python
Classifier: Programming Language :: Python :: 3.6
Classifier: Programming Language :: Python :: 3.7
Classifier: Programming Language :: Python :: 3.8
Classifier: Programming Language :: Python :: 3.9
Classifier: Programming Language :: Python :: 3.10
Classifier: Programming Language :: Python :: 3.11
Classifier: Topic :: Utilities
Classifier: Development Status :: 4 - Beta
